fixedfloat/__init__.py
fixedfloat/fixedfloat.py
fixedfloat_py-0.1.5.dist-info/METADATA
fixedfloat_py-0.1.5.dist-info/WHEEL
fixedfloat_py-0.1.5.dist-info/top_level.txt
fixedfloat_py-0.1.5.dist-info/RECORD
