Metadata-Version: 2.1
Name: fixedfloat-py
Version: 0.1.5
Summary: Python module for FixedFloat API
Home-page: https://github.com/mpp1337/fixedfloat-py
Download-URL: https://pypi.org/project/fixedfloat-py/
Author: mpp1337
Author-email: maxx_uae@protonmail.com
License: MIT
Keywords: FixedFloat,FixedFloat API,Exchanger,Crypto
Platform: UNKNOWN
Requires-Dist: requests
